[{"Prefix":"ст.","Label":"ст. Абаклія, Малдова\n","LabelTail":"Малдова\n","Value":"Абаклія","Gid":"0","Lon":0.0,"Lat":0.0,"Exp":"2300580","Ecp":"0"},{"Prefix":"ст.","Label":"ст. Алексэндрэнь, Малдова\n","LabelTail":"Малдова\n","Value":"Алексэндрэнь","Gid":"0","Lon":0.0,"Lat":0.0,"Exp":"2300572","Ecp":"0"},{"Prefix":"ст.","Label":"ст. Алішкань, Малдова\n","LabelTail":"Малдова\n","Value":"Алішкань","Gid":"0","Lon":0.0,"Lat":0.0,"Exp":"2301595","Ecp":"0"},{"Prefix":"ст.","Label":"ст. Анены, Малдова\n","LabelTail":"Малдова\n","Value":"Анены","Gid":"0","Lon":0.0,"Lat":0.0,"Exp":"2301571","Ecp":"0"},{"Prefix":"ст.","Label":"ст. Басарабяска, Малдова\n","LabelTail":"Малдова\n","Value":"Басарабяска","Gid":"0","Lon":0.0,"Lat":0.0,"Exp":"2300611","Ecp":"0"},{"Prefix":"ст.","Label":"ст. Бахмут, Малдова\n","LabelTail":"Малдова\n","Value":"Бахмут","Gid":"0","Lon":0.0,"Lat":0.0,"Exp":"2300585","Ecp":"0"},{"Prefix":"ст.","Label":"ст. Башкалія, Малдова\n","LabelTail":"Малдова\n","Value":"Башкалія","Gid":"0","Lon":0.0,"Lat":0.0,"Exp":"2300552","Ecp":"0"},{"Prefix":"ст.","Label":"ст. Баюш, Малдова\n","LabelTail":"Малдова\n","Value":"Баюш","Gid":"0","Lon":0.0,"Lat":0.0,"Exp":"2300607","Ecp":"0"},{"Prefix":"ст.","Label":"ст. Беш-Гіëз, Малдова\n","LabelTail":"Малдова\n","Value":"Беш-Гіëз","Gid":"0","Lon":0.0,"Lat":0.0,"Exp":"2300520","Ecp":"0"},{"Prefix":"ст.","Label":"ст. Букавец, Малдова\n","LabelTail":"Малдова\n","Value":"Букавец","Gid":"0","Lon":0.0,"Lat":0.0,"Exp":"2300588","Ecp":"0"},{"Prefix":"ст.","Label":"ст. Булбаака, Малдова\n","LabelTail":"Малдова\n","Value":"Булбаака","Gid":"0","Lon":0.0,"Lat":0.0,"Exp":"2300595","Ecp":"0"},{"Prefix":"ст.","Label":"ст. Бумбэта, Малдова\n","LabelTail":"Малдова\n","Value":"Бумбэта","Gid":"0","Lon":0.0,"Lat":0.0,"Exp":"2301567","Ecp":"0"},{"Prefix":"ст.","Label":"ст. Бучумень, Малдова\n","LabelTail":"Малдова\n","Value":"Бучумень","Gid":"0","Lon":0.0,"Lat":0.0,"Exp":"2300581","Ecp":"0"},{"Prefix":"ст.","Label":"ст. Бырнава, Малдова\n","LabelTail":"Малдова\n","Value":"Бырнава","Gid":"0","Lon":0.0,"Lat":0.0,"Exp":"2301569","Ecp":"0"},{"Prefix":"ст.","Label":"ст. Бэлць-Араш, Малдова\n","LabelTail":"Малдова\n","Value":"Бэлць-Араш","Gid":"0","Lon":27.910277777778,"Lat":47.761111111111,"Exp":"2300574","Ecp":"0"},{"Prefix":"ст.","Label":"ст. Бэлць-Слабозія, Малдова\n","LabelTail":"Малдова\n","Value":"Бэлць-Слабозія","Gid":"0","Lon":27.925833333333,"Lat":47.786111111111,"Exp":"2300620","Ecp":"0"},{"Prefix":"ст.","Label":"ст. Бэндэр 1, Малдова\n","LabelTail":"Малдова\n","Value":"Бэндэр 1","Gid":"0","Lon":0.0,"Lat":0.0,"Exp":"2300590","Ecp":"0"},{"Prefix":"ст.","Label":"ст. Бэндэр 2, Малдова\n","LabelTail":"Малдова\n","Value":"Бэндэр 2","Gid":"0","Lon":0.0,"Lat":0.0,"Exp":"2300597","Ecp":"0"},{"Prefix":"ст.","Label":"ст. Бярэшты, Малдова\n","LabelTail":"Малдова\n","Value":"Бярэшты","Gid":"0","Lon":27.801111111111,"Lat":47.231944444444,"Exp":"2301554","Ecp":"0"},{"Prefix":"ст.","Label":"ст. Варанкова, Малдова\n","LabelTail":"Малдова\n","Value":"Варанкова","Gid":"0","Lon":0.0,"Lat":0.0,"Exp":"2300561","Ecp":"0"},{"Prefix":"ст.","Label":"ст. Варцікоўцы, Малдова\n","LabelTail":"Малдова\n","Value":"Варцікоўцы","Gid":"0","Lon":0.0,"Lat":0.0,"Exp":"2300237","Ecp":"0"},{"Prefix":"ст.","Label":"ст. Веражаны, Малдова\n","LabelTail":"Малдова\n","Value":"Веражаны","Gid":"0","Lon":0.0,"Lat":0.0,"Exp":"2300106","Ecp":"0"},{"Prefix":"ст.","Label":"ст. Вісцернічань, Малдова\n","LabelTail":"Малдова\n","Value":"Вісцернічань","Gid":"0","Lon":0.0,"Lat":0.0,"Exp":"2301550","Ecp":"0"},{"Prefix":"ст.","Label":"ст. Вулкэнешць, Малдова\n","LabelTail":"Малдова\n","Value":"Вулкэнешць","Gid":"0","Lon":0.0,"Lat":0.0,"Exp":"2300573","Ecp":"0"},{"Prefix":"ст.","Label":"ст. Вэлчынец, Малдова\n","LabelTail":"Малдова\n","Value":"Вэлчынец","Gid":"0","Lon":27.735833333333,"Lat":48.450555555556,"Exp":"2300547","Ecp":"0"},{"Prefix":"ст.","Label":"ст. Гацешць, Малдова\n","LabelTail":"Малдова\n","Value":"Гацешць","Gid":"0","Lon":0.0,"Lat":0.0,"Exp":"2301552","Ecp":"0"},{"Prefix":"ст.","Label":"ст. Гершуноўка, Малдова\n","LabelTail":"Малдова\n","Value":"Гершуноўка","Gid":"0","Lon":0.0,"Lat":0.0,"Exp":"2301598","Ecp":"0"},{"Prefix":"ст.","Label":"ст. Гідыгіч, Малдова\n","LabelTail":"Малдова\n","Value":"Гідыгіч","Gid":"0","Lon":0.0,"Lat":0.0,"Exp":"2300591","Ecp":"0"},{"Prefix":"ст.","Label":"ст. Гіздзіта, Малдова\n","LabelTail":"Малдова\n","Value":"Гіздзіта","Gid":"0","Lon":0.0,"Lat":0.0,"Exp":"2301576","Ecp":"0"},{"Prefix":"ст.","Label":"ст. Гіндэшць, Малдова\n","LabelTail":"Малдова\n","Value":"Гіндэшць","Gid":"0","Lon":0.0,"Lat":0.0,"Exp":"2300569","Ecp":"0"},{"Prefix":"ст.","Label":"ст. Грачэнь, Малдова\n","LabelTail":"Малдова\n","Value":"Грачэнь","Gid":"0","Lon":0.0,"Lat":0.0,"Exp":"2300618","Ecp":"0"},{"Prefix":"ст.","Label":"ст. Грынаўцы, Малдова\n","LabelTail":"Малдова\n","Value":"Грынаўцы","Gid":"0","Lon":0.0,"Lat":0.0,"Exp":"2300535","Ecp":"0"},{"Prefix":"ст.","Label":"ст. Гура-Кайнары, Малдова\n","LabelTail":"Малдова\n","Value":"Гура-Кайнары","Gid":"0","Lon":0.0,"Lat":0.0,"Exp":"2300525","Ecp":"0"},{"Prefix":"ст.","Label":"ст. Гура-Каменчы, Малдова\n","LabelTail":"Малдова\n","Value":"Гура-Каменчы","Gid":"0","Lon":0.0,"Lat":0.0,"Exp":"2301593","Ecp":"0"},{"Prefix":"ст.","Label":"ст. Гырбава, Малдова\n","LabelTail":"Малдова\n","Value":"Гырбава","Gid":"0","Lon":0.0,"Lat":0.0,"Exp":"2301581","Ecp":"0"},{"Prefix":"ст.","Label":"ст. Гыртоп, Малдова\n","LabelTail":"Малдова\n","Value":"Гыртоп","Gid":"0","Lon":0.0,"Lat":0.0,"Exp":"2300604","Ecp":"0"},{"Prefix":"ст.","Label":"ст. Дандзюшэнь, Малдова\n","LabelTail":"Малдова\n","Value":"Дандзюшэнь","Gid":"0","Lon":27.609166666667,"Lat":48.235277777778,"Exp":"2300554","Ecp":"0"},{"Prefix":"ст.","Label":"ст. Джалтай, Малдова\n","LabelTail":"Малдова\n","Value":"Джалтай","Gid":"0","Lon":0.0,"Lat":0.0,"Exp":"2301556","Ecp":"0"},{"Prefix":"ст.","Label":"ст. Дзезгінжэны, Малдова\n","LabelTail":"Малдова\n","Value":"Дзезгінжэны","Gid":"0","Lon":0.0,"Lat":0.0,"Exp":"2300596","Ecp":"0"},{"Prefix":"ст.","Label":"ст. Дрокія, Малдова\n","LabelTail":"Малдова\n","Value":"Дрокія","Gid":"0","Lon":27.81,"Lat":48.030833333333,"Exp":"2300557","Ecp":"0"},{"Prefix":"ст.","Label":"ст. Елізаветаўка, Малдова\n","LabelTail":"Малдова\n","Value":"Елізаветаўка","Gid":"0","Lon":0.0,"Lat":0.0,"Exp":"2301591","Ecp":"0"},{"Prefix":"ст.","Label":"ст. Жэмчуг, Малдова\n","LabelTail":"Малдова\n","Value":"Жэмчуг","Gid":"0","Lon":0.0,"Lat":0.0,"Exp":"2301563","Ecp":"0"},{"Prefix":"ст.","Label":"ст. Заім, Малдова\n","LabelTail":"Малдова\n","Value":"Заім","Gid":"0","Lon":0.0,"Lat":0.0,"Exp":"2300603","Ecp":"0"},{"Prefix":"ст.","Label":"ст. Запасны Код, Малдова\n","LabelTail":"Малдова\n","Value":"Запасны Код","Gid":"0","Lon":0.0,"Lat":0.0,"Exp":"2300504","Ecp":"0"},{"Prefix":"ст.","Label":"ст. Зернешты, Малдова\n","LabelTail":"Малдова\n","Value":"Зернешты","Gid":"0","Lon":0.0,"Lat":0.0,"Exp":"2300632","Ecp":"0"},{"Prefix":"ст.","Label":"ст. Злоць, Малдова\n","LabelTail":"Малдова\n","Value":"Злоць","Gid":"0","Lon":0.0,"Lat":0.0,"Exp":"2300606","Ecp":"0"},{"Prefix":"ст.","Label":"ст. Іванаўка, Малдова\n","LabelTail":"Малдова\n","Value":"Іванаўка","Gid":"0","Lon":0.0,"Lat":0.0,"Exp":"2300537","Ecp":"0"},{"Prefix":"ст.","Label":"ст. Іссерлія, Малдова\n","LabelTail":"Малдова\n","Value":"Іссерлія","Gid":"0","Lon":0.0,"Lat":0.0,"Exp":"2301507","Ecp":"0"},{"Prefix":"ст.","Label":"ст. Ліпень, Малдова\n","LabelTail":"Малдова\n","Value":"Ліпень","Gid":"0","Lon":0.0,"Lat":0.0,"Exp":"2300563","Ecp":"0"},{"Prefix":"ст.","Label":"ст. Ліпкань, Малдова\n","LabelTail":"Малдова\n","Value":"Ліпкань","Gid":"0","Lon":0.0,"Lat":0.0,"Exp":"2300035","Ecp":"0"},{"Prefix":"ст.","Label":"ст. Мар'янка, Малдова\n","LabelTail":"Малдова\n","Value":"Мар'янка","Gid":"0","Lon":0.0,"Lat":0.0,"Exp":"2301533","Ecp":"0"},{"Prefix":"ст.","Label":"ст. Мацеуць, Малдова\n","LabelTail":"Малдова\n","Value":"Мацеуць","Gid":"0","Lon":0.0,"Lat":0.0,"Exp":"2300626","Ecp":"0"},{"Prefix":"ст.","Label":"ст. Медзялень, Малдова\n","LabelTail":"Малдова\n","Value":"Медзялень","Gid":"0","Lon":0.0,"Lat":0.0,"Exp":"2301560","Ecp":"0"},{"Prefix":"ст.","Label":"ст. Мерэнь, Малдова\n","LabelTail":"Малдова\n","Value":"Мерэнь","Gid":"0","Lon":0.0,"Lat":0.0,"Exp":"2300593","Ecp":"0"},{"Prefix":"ст.","Label":"ст. Мікалаеўка, Малдова\n","LabelTail":"Малдова\n","Value":"Мікалаеўка","Gid":"0","Lon":0.0,"Lat":0.0,"Exp":"2301562","Ecp":"0"},{"Prefix":"ст.","Label":"ст. Мэркулешць, Малдова\n","LabelTail":"Малдова\n","Value":"Мэркулешць","Gid":"0","Lon":0.0,"Lat":0.0,"Exp":"2300571","Ecp":"0"},{"Prefix":"ст.","Label":"ст. Мядзведжа, Малдова\n","LabelTail":"Малдова\n","Value":"Мядзведжа","Gid":"0","Lon":0.0,"Lat":0.0,"Exp":"2300236","Ecp":"0"},{"Prefix":"ст.","Label":"ст. Наслаўча, Малдова\n","LabelTail":"Малдова\n","Value":"Наслаўча","Gid":"0","Lon":0.0,"Lat":0.0,"Exp":"2301575","Ecp":"0"},{"Prefix":"ст.","Label":"ст. Новасавіцкая, Малдова\n","LabelTail":"Малдова\n","Value":"Новасавіцкая","Gid":"0","Lon":0.0,"Lat":0.0,"Exp":"2300536","Ecp":"0"},{"Prefix":"ст.","Label":"ст. Пагорна, Малдова\n","LabelTail":"Малдова\n","Value":"Пагорна","Gid":"0","Lon":0.0,"Lat":0.0,"Exp":"2300120","Ecp":"0"},{"Prefix":"ст.","Label":"ст. Пеленей, Малдова\n","LabelTail":"Малдова\n","Value":"Пеленей","Gid":"0","Lon":0.0,"Lat":0.0,"Exp":"2300117","Ecp":"0"},{"Prefix":"ст.","Label":"ст. Пераезд, Малдова\n","LabelTail":"Малдова\n","Value":"Пераезд","Gid":"0","Lon":0.0,"Lat":0.0,"Exp":"2301501","Ecp":"0"},{"Prefix":"ст.","Label":"ст. Петрэшты, Малдова\n","LabelTail":"Малдова\n","Value":"Петрэшты","Gid":"0","Lon":27.745277777778,"Lat":47.287777777778,"Exp":"2300582","Ecp":"0"},{"Prefix":"ст.","Label":"ст. Пост 8 км, Малдова\n","LabelTail":"Малдова\n","Value":"Пост 8 км","Gid":"0","Lon":0.0,"Lat":0.0,"Exp":"2300623","Ecp":"0"},{"Prefix":"ст.","Label":"ст. Прункул, Малдова\n","LabelTail":"Малдова\n","Value":"Прункул","Gid":"0","Lon":0.0,"Lat":0.0,"Exp":"2301574","Ecp":"0"},{"Prefix":"ст.","Label":"ст. Прут, Малдова\n","LabelTail":"Малдова\n","Value":"Прут","Gid":"0","Lon":0.0,"Lat":0.0,"Exp":"2301585","Ecp":"0"},{"Prefix":"ст.","Label":"ст. Прут 3, Малдова\n","LabelTail":"Малдова\n","Value":"Прут 3","Gid":"0","Lon":0.0,"Lat":0.0,"Exp":"2301584","Ecp":"0"},{"Prefix":"ст.","Label":"ст. Прып. пункт 106 км, Малдова\n","LabelTail":"Малдова\n","Value":"Прып. пункт 106 км","Gid":"0","Lon":0.0,"Lat":0.0,"Exp":"2301596","Ecp":"0"},{"Prefix":"ст.","Label":"ст. Пуцінэшць, Малдова\n","LabelTail":"Малдова\n","Value":"Пуцінэшць","Gid":"0","Lon":0.0,"Lat":0.0,"Exp":"2301592","Ecp":"0"},{"Prefix":"ст.","Label":"ст. Пырліца, Малдова\n","LabelTail":"Малдова\n","Value":"Пырліца","Gid":"0","Lon":0.0,"Lat":0.0,"Exp":"2300583","Ecp":"0"},{"Prefix":"ст.","Label":"ст. Пэнэшэшць, Малдова\n","LabelTail":"Малдова\n","Value":"Пэнэшэшць","Gid":"0","Lon":0.0,"Lat":0.0,"Exp":"2301570","Ecp":"0"},{"Prefix":"ст.","Label":"ст. Рагажэнь, Малдова\n","LabelTail":"Малдова\n","Value":"Рагажэнь","Gid":"0","Lon":0.0,"Lat":0.0,"Exp":"2300567","Ecp":"0"},{"Prefix":"ст.","Label":"ст. Раз'езд 208 км, Малдова\n","LabelTail":"Малдова\n","Value":"Раз'езд 208 км","Gid":"0","Lon":0.0,"Lat":0.0,"Exp":"2300107","Ecp":"0"},{"Prefix":"ст.","Label":"ст. Раз'езд 34 км, Малдова\n","LabelTail":"Малдова\n","Value":"Раз'езд 34 км","Gid":"0","Lon":0.0,"Lat":0.0,"Exp":"2301589","Ecp":"0"},{"Prefix":"ст.","Label":"ст. Раз'езд 67 км, Малдова\n","LabelTail":"Малдова\n","Value":"Раз'езд 67 км","Gid":"0","Lon":0.0,"Lat":0.0,"Exp":"2301506","Ecp":"0"},{"Prefix":"ст.","Label":"ст. Рамашка, Малдова\n","LabelTail":"Малдова\n","Value":"Рамашка","Gid":"0","Lon":0.0,"Lat":0.0,"Exp":"2301573","Ecp":"0"},{"Prefix":"ст.","Label":"ст. Ревака, Малдова\n","LabelTail":"Малдова\n","Value":"Ревака","Gid":"0","Lon":0.0,"Lat":0.0,"Exp":"2301582","Ecp":"0"},{"Prefix":"ст.","Label":"ст. Редзіул-Марэ, Малдова\n","LabelTail":"Малдова\n","Value":"Редзіул-Марэ","Gid":"0","Lon":27.4925,"Lat":48.269444444444,"Exp":"2300553","Ecp":"0"},{"Prefix":"ст.","Label":"ст. Рошкань, Малдова\n","LabelTail":"Малдова\n","Value":"Рошкань","Gid":"0","Lon":0.0,"Lat":0.0,"Exp":"2301555","Ecp":"0"},{"Prefix":"ст.","Label":"ст. Рыбніца, Малдова\n","LabelTail":"Малдова\n","Value":"Рыбніца","Gid":"0","Lon":0.0,"Lat":0.0,"Exp":"2300562","Ecp":"0"},{"Prefix":"ст.","Label":"ст. Рэвуцел, Малдова\n","LabelTail":"Малдова\n","Value":"Рэвуцел","Gid":"0","Lon":0.0,"Lat":0.0,"Exp":"2300575","Ecp":"0"},{"Prefix":"ст.","Label":"ст. Сакалень, Малдова\n","LabelTail":"Малдова\n","Value":"Сакалень","Gid":"0","Lon":0.0,"Lat":0.0,"Exp":"2300594","Ecp":"0"},{"Prefix":"ст.","Label":"ст. Сату-Ноу, Малдова\n","LabelTail":"Малдова\n","Value":"Сату-Ноу","Gid":"0","Lon":0.0,"Lat":0.0,"Exp":"2301557","Ecp":"0"},{"Prefix":"ст.","Label":"ст. Саўхоз, Малдова\n","LabelTail":"Малдова\n","Value":"Саўхоз","Gid":"0","Lon":0.0,"Lat":0.0,"Exp":"2301551","Ecp":"0"},{"Prefix":"ст.","Label":"ст. Сафія, Малдова\n","LabelTail":"Малдова\n","Value":"Сафія","Gid":"0","Lon":27.836944444444,"Lat":47.954444444444,"Exp":"2300558","Ecp":"0"},{"Prefix":"ст.","Label":"ст. Селемет, Малдова\n","LabelTail":"Малдова\n","Value":"Селемет","Gid":"0","Lon":0.0,"Lat":0.0,"Exp":"2301583","Ecp":"0"},{"Prefix":"ст.","Label":"ст. Серпнева 1, Малдова\n","LabelTail":"Малдова\n","Value":"Серпнева 1","Gid":"0","Lon":0.0,"Lat":0.0,"Exp":"2300461","Ecp":"0"},{"Prefix":"ст.","Label":"ст. Сіпацены, Малдова\n","LabelTail":"Малдова\n","Value":"Сіпацены","Gid":"0","Lon":0.0,"Lat":0.0,"Exp":"2300586","Ecp":"0"},{"Prefix":"ст.","Label":"ст. Стаянаўка, Малдова\n","LabelTail":"Малдова\n","Value":"Стаянаўка","Gid":"0","Lon":0.0,"Lat":0.0,"Exp":"2300624","Ecp":"0"},{"Prefix":"ст.","Label":"ст. Стольнічаны, Малдова\n","LabelTail":"Малдова\n","Value":"Стольнічаны","Gid":"0","Lon":0.0,"Lat":0.0,"Exp":"2300498","Ecp":"0"},{"Prefix":"ст.","Label":"ст. Страшэнь, Малдова\n","LabelTail":"Малдова\n","Value":"Страшэнь","Gid":"0","Lon":28.619722222222,"Lat":47.149722222222,"Exp":"2300589","Ecp":"0"},{"Prefix":"ст.","Label":"ст. Сынжара, Малдова\n","LabelTail":"Малдова\n","Value":"Сынжара","Gid":"0","Lon":0.0,"Lat":0.0,"Exp":"2301572","Ecp":"0"},{"Prefix":"ст.","Label":"ст. Сэлкуца, Малдова\n","LabelTail":"Малдова\n","Value":"Сэлкуца","Gid":"0","Lon":0.0,"Lat":0.0,"Exp":"2301505","Ecp":"0"},{"Prefix":"ст.","Label":"ст. Сэрата Веке, Малдова\n","LabelTail":"Малдова\n","Value":"Сэрата Веке","Gid":"0","Lon":0.0,"Lat":0.0,"Exp":"2300579","Ecp":"0"},{"Prefix":"ст.","Label":"ст. Сяло-Калфа, Малдова\n","LabelTail":"Малдова\n","Value":"Сяло-Калфа","Gid":"0","Lon":0.0,"Lat":0.0,"Exp":"2301590","Ecp":"0"},{"Prefix":"ст.","Label":"ст. Тараклія, Малдова\n","LabelTail":"Малдова\n","Value":"Тараклія","Gid":"0","Lon":0.0,"Lat":0.0,"Exp":"2300616","Ecp":"0"},{"Prefix":"ст.","Label":"ст. Татарашэны, Малдова\n","LabelTail":"Малдова\n","Value":"Татарашэны","Gid":"0","Lon":0.0,"Lat":0.0,"Exp":"2300622","Ecp":"0"},{"Prefix":"ст.","Label":"ст. Тырнава, Малдова\n","LabelTail":"Малдова\n","Value":"Тырнава","Gid":"0","Lon":0.0,"Lat":0.0,"Exp":"2300555","Ecp":"0"},{"Prefix":"ст.","Label":"ст. Унгень, Малдова\n","LabelTail":"Малдова\n","Value":"Унгень","Gid":"0","Lon":0.0,"Lat":0.0,"Exp":"2300145","Ecp":"0"},{"Prefix":"ст.","Label":"ст. Ункіцешць, Малдова\n","LabelTail":"Малдова\n","Value":"Ункіцешць","Gid":"0","Lon":0.0,"Lat":0.0,"Exp":"2300566","Ecp":"0"},{"Prefix":"ст.","Label":"ст. Унцешць, Малдова\n","LabelTail":"Малдова\n","Value":"Унцешць","Gid":"0","Lon":27.9075,"Lat":47.227777777778,"Exp":"2301564","Ecp":"0"},{"Prefix":"ст.","Label":"ст. Фалешць, Малдова\n","LabelTail":"Малдова\n","Value":"Фалешць","Gid":"0","Lon":27.740833333333,"Lat":47.549166666667,"Exp":"2300578","Ecp":"0"},{"Prefix":"ст.","Label":"ст. Фларэшць, Малдова\n","LabelTail":"Малдова\n","Value":"Фларэшць","Gid":"0","Lon":0.0,"Lat":0.0,"Exp":"2300466","Ecp":"0"},{"Prefix":"ст.","Label":"ст. Хаджымус, Малдова\n","LabelTail":"Малдова\n","Value":"Хаджымус","Gid":"0","Lon":0.0,"Lat":0.0,"Exp":"2300601","Ecp":"0"},{"Prefix":"ст.","Label":"ст. Хіліуць, Малдова\n","LabelTail":"Малдова\n","Value":"Хіліуць","Gid":"0","Lon":0.0,"Lat":0.0,"Exp":"2300576","Ecp":"0"},{"Prefix":"ст.","Label":"ст. Ціраспал, Малдова\n","LabelTail":"Малдова\n","Value":"Ціраспал","Gid":"0","Lon":0.0,"Lat":0.0,"Exp":"2300610","Ecp":"0"},{"Prefix":"ст.","Label":"ст. Цыра, Малдова\n","LabelTail":"Малдова\n","Value":"Цыра","Gid":"0","Lon":0.0,"Lat":0.0,"Exp":"2300568","Ecp":"0"},{"Prefix":"ст.","Label":"ст. Чадыр-Лунга, Малдова\n","LabelTail":"Малдова\n","Value":"Чадыр-Лунга","Gid":"0","Lon":0.0,"Lat":0.0,"Exp":"2300614","Ecp":"0"},{"Prefix":"ст.","Label":"ст. Чок-Майдан, Малдова\n","LabelTail":"Малдова\n","Value":"Чок-Майдан","Gid":"0","Lon":0.0,"Lat":0.0,"Exp":"2301566","Ecp":"0"},{"Prefix":"ст.","Label":"ст. Чуфлешць, Малдова\n","LabelTail":"Малдова\n","Value":"Чуфлешць","Gid":"0","Lon":0.0,"Lat":0.0,"Exp":"2301565","Ecp":"0"},{"Prefix":"ст.","Label":"ст. Чымішлія, Малдова\n","LabelTail":"Малдова\n","Value":"Чымішлія","Gid":"0","Lon":0.0,"Lat":0.0,"Exp":"2300608","Ecp":"0"},{"Prefix":"ст.","Label":"ст. Чэкур-Менжыр, Малдова\n","LabelTail":"Малдова\n","Value":"Чэкур-Менжыр","Gid":"0","Lon":0.0,"Lat":0.0,"Exp":"2300556","Ecp":"0"},{"Prefix":"ст.","Label":"ст. Чэнак, Малдова\n","LabelTail":"Малдова\n","Value":"Чэнак","Gid":"0","Lon":0.0,"Lat":0.0,"Exp":"2300598","Ecp":"0"},{"Prefix":"ст.","Label":"ст. Чэрапканий Ной, Малдова\n","LabelTail":"Малдова\n","Value":"Чэрапканий Ной","Gid":"0","Lon":0.0,"Lat":0.0,"Exp":"2301558","Ecp":"0"},{"Prefix":"ст.","Label":"ст. Шаўдынешць, Малдова\n","LabelTail":"Малдова\n","Value":"Шаўдынешць","Gid":"0","Lon":0.0,"Lat":0.0,"Exp":"2300564","Ecp":"0"},{"Prefix":"ст.","Label":"ст. Шаўковы Камбінат, Малдова\n","LabelTail":"Малдова\n","Value":"Шаўковы Камбінат","Gid":"0","Lon":0.0,"Lat":0.0,"Exp":"2301503","Ecp":"0"},{"Prefix":"ст.","Label":"ст. Яргара, Малдова\n","LabelTail":"Малдова\n","Value":"Яргара","Gid":"0","Lon":0.0,"Lat":0.0,"Exp":"2301561","Ecp":"0"},{"Prefix":"ст.","Label":"ст. Ятулія, Малдова\n","LabelTail":"Малдова\n","Value":"Ятулія","Gid":"0","Lon":0.0,"Lat":0.0,"Exp":"2300619","Ecp":"0"}]